AUTHORS.rst
CONTRIBUTING.rst
HISTORY.rst
LICENSE
MANIFEST.in
README.rst
setup.cfg
setup.py
docs/Makefile
docs/authors.rst
docs/conf.py
docs/contributing.rst
docs/history.rst
docs/index.rst
docs/installation.rst
docs/make.bat
docs/readme.rst
docs/usage.rst
sheath_fluid/__init__.py
sheath_fluid/fluid.py
sheath_fluid/sheath_fluid.py
sheath_fluid.egg-info/PKG-INFO
sheath_fluid.egg-info/SOURCES.txt
sheath_fluid.egg-info/dependency_links.txt
sheath_fluid.egg-info/not-zip-safe
sheath_fluid.egg-info/requires.txt
sheath_fluid.egg-info/top_level.txt
tests/test_sheath_fluid.py