Metadata-Version: 1.1
Name: sheath-fluid
Version: 0.2.0
Summary: Solve the stationnary collisionless plasma sheath model using polytropic law as electr energy equation closure
Home-page: https://github.com/antoinelpp/sheath_fluid
Author: Antoine Tavant
Author-email: antoinetavant@hotmail.fr
License: GNU General Public License v3
Download-URL: https://github.com/antoinelpp/sheath_fluid/archive/0.2.tar.gz
Keywords: sheath_fluid
Platform: UNKNOWN
Classifier: Development Status :: 2 - Pre-Alpha
Classifier: Intended Audience :: Developers
Classifier: License :: OSI Approved :: GNU General Public License v3 (GPLv3)
Classifier: Natural Language :: English
Classifier: Programming Language :: Python :: 3.6
Classifier: Programming Language :: Python :: 3.7
